orpheum/A00111:467:H737CDSXY:2:1603:1398:5541   CB:Z:AAGAT
orpheum/__init__.py
orpheum/commandline.py
orpheum/common.py
orpheum/compare_kmer_content.py
orpheum/constants_index.py
orpheum/constants_translate.py
orpheum/create_save_summary.py
orpheum/downsample_hashes.py
orpheum/ensembl.py
orpheum/extract_metadata.py
orpheum/holoviews.py
orpheum/homology.py
orpheum/idf.py
orpheum/index.py
orpheum/jaccard_utils.py
orpheum/jupyter_utils.py
orpheum/knn.py
orpheum/log_utils.py
orpheum/os_utils.py
orpheum/s3_utils.py
orpheum/sequence_encodings.py
orpheum/sourmash_compare_utils.py
orpheum/sourmash_utils.py
orpheum/translate.py
orpheum/translate_single_seq.py
orpheum/version.py
orpheum-1.0.4.dist-info/AUTHORS.md
orpheum-1.0.4.dist-info/LICENSE
orpheum-1.0.4.dist-info/METADATA
orpheum-1.0.4.dist-info/WHEEL
orpheum-1.0.4.dist-info/entry_points.txt
orpheum-1.0.4.dist-info/top_level.txt
orpheum-1.0.4.dist-info/RECORD
