Metadata-Version: 2.1
Name: orpheum
Version: 1.0.4
Summary: Sencha is a Python package for directly translating RNA-seq reads into coding protein sequence.
Home-page: https://github.com/czbiohub/orpheum
Author: Olga Botvinnik
Author-email: olga.botvinnik@czbiohub.org
License: MIT
Keywords: orpheum
Platform: UNKNOWN
Classifier: Development Status :: 2 - Pre-Alpha
Classifier: Intended Audience :: Developers
Classifier: License :: OSI Approved :: MIT License
Classifier: Natural Language :: English
Classifier: Programming Language :: Python :: 3
Classifier: Programming Language :: Python :: 3.6
Classifier: Programming Language :: Python :: 3.7
Requires-Dist: click
Requires-Dist: httmock
Requires-Dist: khmer
Requires-Dist: networkx
Requires-Dist: numpy
Requires-Dist: pandas
Requires-Dist: scikit-learn
Requires-Dist: seaborn
Requires-Dist: sourmash
Requires-Dist: tqdm
Requires-Dist: ipykernel
Requires-Dist: joblib
Requires-Dist: notebook
Requires-Dist: pyarrow
Requires-Dist: s3fs
Requires-Dist: fastparquet
Requires-Dist: pytest
